[
  {
    "url": "https://www.npi-tu.ru/",
    "technologies": [
      {
        "slug": "cdnjs",
        "name": "cdnjs",
        "versions": [],
        "trafficRank": 117,
        "confirmedAt": 1635676105,
        "categories": [
          {
            "id": 31,
            "slug": "cdn",
            "name": "CDN"
          }
        ]
      },
      {
        "slug": "google-tag-manager",
        "name": "Google Tag Manager",
        "versions": [],
        "trafficRank": 154,
        "confirmedAt": 1635676104,
        "categories": [
          {
            "id": 42,
            "slug": "tag-managers",
            "name": "Tag managers"
          }
        ]
      },
      {
        "slug": "core-js",
        "name": "core-js",
        "versions": [
          "2.6.3"
        ],
        "trafficRank": 154,
        "confirmedAt": 1635676105,
        "categories": [
          {
            "id": 59,
            "slug": "javascript-libraries",
            "name": "JavaScript libraries"
          }
        ]
      },
      {
        "slug": "fancybox",
        "name": "FancyBox",
        "versions": [
          "3.5.2"
        ],
        "trafficRank": 154,
        "confirmedAt": 1635676104,
        "categories": [
          {
            "id": 59,
            "slug": "javascript-libraries",
            "name": "JavaScript libraries"
          }
        ]
      },
      {
        "slug": "swiper-slider",
        "name": "Swiper Slider",
        "versions": [],
        "trafficRank": 154,
        "confirmedAt": 1635676104,
        "categories": [
          {
            "id": 19,
            "slug": "miscellaneous",
            "name": "Miscellaneous"
          }
        ]
      },
      {
        "slug": "bootstrap",
        "name": "Bootstrap",
        "versions": [
          "1.6.2",
          "4.3.1"
        ],
        "trafficRank": 154,
        "confirmedAt": 1635676104,
        "categories": [
          {
            "id": 66,
            "slug": "ui-frameworks",
            "name": "UI frameworks"
          }
        ]
      },
      {
        "slug": "google-remarketing-tag",
        "name": "Google Remarketing Tag",
        "versions": [],
        "trafficRank": 154,
        "confirmedAt": 1635676104,
        "categories": [
          {
            "id": 77,
            "slug": "retargeting",
            "name": "Retargeting"
          }
        ]
      },
      {
        "slug": "google-font-api",
        "name": "Google Font API",
        "versions": [],
        "trafficRank": 161,
        "confirmedAt": 1635676105,
        "categories": [
          {
            "id": 17,
            "slug": "font-scripts",
            "name": "Font scripts"
          }
        ]
      },
      {
        "slug": "php",
        "name": "PHP",
        "versions": [],
        "trafficRank": 161,
        "confirmedAt": 1635676104,
        "categories": [
          {
            "id": 27,
            "slug": "programming-languages",
            "name": "Programming languages"
          }
        ]
      },
      {
        "slug": "jquery",
        "name": "jQuery",
        "versions": [
          "1.8.3",
          "3.3.1"
        ],
        "trafficRank": 161,
        "confirmedAt": 1635676104,
        "categories": [
          {
            "id": 59,
            "slug": "javascript-libraries",
            "name": "JavaScript libraries"
          }
        ]
      },
      {
        "slug": "yandex-metrika",
        "name": "Yandex.Metrika",
        "versions": [],
        "trafficRank": 161,
        "confirmedAt": 1635676105,
        "categories": [
          {
            "id": 10,
            "slug": "analytics",
            "name": "Analytics"
          }
        ]
      },
      {
        "slug": "nginx",
        "name": "Nginx",
        "versions": [],
        "trafficRank": 161,
        "confirmedAt": 1635676104,
        "categories": [
          {
            "id": 22,
            "slug": "web-servers",
            "name": "Web servers"
          },
          {
            "id": 64,
            "slug": "reverse-proxies",
            "name": "Reverse proxies"
          }
        ]
      },
      {
        "slug": "1c-bitrix",
        "name": "1C-Bitrix",
        "versions": [],
        "trafficRank": 161,
        "confirmedAt": 1635676104,
        "categories": [
          {
            "id": 1,
            "slug": "cms",
            "name": "CMS"
          },
          {
            "id": 6,
            "slug": "ecommerce",
            "name": "Ecommerce"
          }
        ]
      },
      {
        "slug": "google-analytics",
        "name": "Google Analytics",
        "versions": [],
        "trafficRank": 161,
        "confirmedAt": 1635676105,
        "categories": [
          {
            "id": 10,
            "slug": "analytics",
            "name": "Analytics"
          }
        ]
      }
    ]
  }
]